MoralisPy/__init__.py
MoralisPy/api.py
MoralisPy-1.0.1.dist-info/LICENSE
MoralisPy-1.0.1.dist-info/METADATA
MoralisPy-1.0.1.dist-info/WHEEL
MoralisPy-1.0.1.dist-info/top_level.txt
MoralisPy-1.0.1.dist-info/RECORD
