Metadata-Version: 2.1
Name: MoralisPy
Version: 1.0.1
Summary: A python wrapper for the Molaris REST API
Home-page: https://github.com/bberg/MoralisPy
Author: Ben Berg
Author-email: benberg00@gmail.com
License: GNU General Public License v3.0
Platform: UNKNOWN
License-File: LICENSE
Requires-Dist: requests
